cool_django_auth_ldap/__init__.py
cool_django_auth_ldap/admin.py
cool_django_auth_ldap/apps.py
cool_django_auth_ldap/backend.py
cool_django_auth_ldap/config.py
cool_django_auth_ldap/models.py
cool_django_auth_ldap/migrations/0001_initial.py
cool_django_auth_ldap/migrations/__init__.py
cool_django_auth_ldap-1.1.3.dist-info/AUTHORS
cool_django_auth_ldap-1.1.3.dist-info/AUTHORS.rst
cool_django_auth_ldap-1.1.3.dist-info/LICENSE
cool_django_auth_ldap-1.1.3.dist-info/METADATA
cool_django_auth_ldap-1.1.3.dist-info/WHEEL
cool_django_auth_ldap-1.1.3.dist-info/pbr.json
cool_django_auth_ldap-1.1.3.dist-info/top_level.txt
cool_django_auth_ldap-1.1.3.dist-info/RECORD
